xinqing/__init__.py
xinqing/playsound122.py
xinqing/typing_long.mp3
xinqing/xinqing.py
xinqing-0.1.0.data/data/xinqing/typing_long.mp3
xinqing-0.1.0.dist-info/METADATA
xinqing-0.1.0.dist-info/WHEEL
xinqing-0.1.0.dist-info/top_level.txt
xinqing-0.1.0.dist-info/RECORD
