Metadata-Version: 2.1
Name: xinqing
Version: 0.1.0
Summary: A class describes a person.
Home-page: UNKNOWN
Author: heihei
Author-email: heihei@hh.com
License: UNKNOWN
Platform: UNKNOWN
Classifier: Programming Language :: Python :: 3
Classifier: License :: OSI Approved :: MIT License
Classifier: Operating System :: OS Independent
Requires-Python: >3
